pytest_flask/__init__.py
pytest_flask/_internal.py
pytest_flask/_version.py
pytest_flask/fixtures.py
pytest_flask/live_server.py
pytest_flask/plugin.py
pytest_flask/pytest_compat.py
pytest_flask-1.3.0.dist-info/LICENSE
pytest_flask-1.3.0.dist-info/METADATA
pytest_flask-1.3.0.dist-info/WHEEL
pytest_flask-1.3.0.dist-info/entry_points.txt
pytest_flask-1.3.0.dist-info/top_level.txt
pytest_flask-1.3.0.dist-info/RECORD
