Metadata-Version: 2.1
Name: pytest-flask
Version: 1.3.0
Summary: A set of py.test fixtures to test Flask applications.
Home-page: https://github.com/pytest-dev/pytest-flask
Author: Vital Kudzelka
Author-email: vital.kudzelka@gmail.com
License: MIT
Project-URL: Source, https://github.com/pytest-dev/pytest-flask
Project-URL: Issue tracker, https://github.com/pytest-dev/pytest-flask/issues
Keywords: pytest,flask,testing
Classifier: Framework :: Pytest
Classifier: Environment :: Plugins
Classifier: Programming Language :: Python
Classifier: Environment :: Web Environment
Classifier: Intended Audience :: Developers
Classifier: Operating System :: OS Independent
Classifier: Programming Language :: Python :: 3.7
Classifier: Programming Language :: Python :: 3.8
Classifier: Programming Language :: Python :: 3.9
Classifier: License :: OSI Approved :: MIT License
Classifier: Topic :: Software Development :: Testing
Classifier: Development Status :: 5 - Production/Stable
Classifier: Topic :: Software Development :: Libraries :: Python Modules
Requires-Python: >=3.7
License-File: LICENSE
Requires-Dist: pytest>=5.2
Requires-Dist: Flask
Requires-Dist: Werkzeug
Provides-Extra: docs
Requires-Dist: Sphinx; extra == "docs"
Requires-Dist: sphinx_rtd_theme; extra == "docs"
Provides-Extra: tests
